[{"年度":1998,"總計":null,"台灣地區":28303,"新北市":2531,"台北市":675,"桃園市":2676,"台中市":3501,"台南市":2699,"高雄市":3182,"宜蘭縣":1235,"新竹縣":1257,"苗栗縣":1117,"彰化縣":1290,"南投縣":408,"雲林縣":2193,"嘉義縣":1650,"屏東縣":1697,"台東縣":140,"花蓮縣":609,"澎湖縣":345,"基隆市":379,"新竹市":402,"嘉義市":317,"金門縣":null,"連江縣":null},{"年度":1999,"總計":null,"台灣地區":27807,"新北市":3113,"台北市":681,"桃園市":2032,"台中市":2956,"台南市":3306,"高雄市":3229,"宜蘭縣":820,"新竹縣":1168,"苗栗縣":1136,"彰化縣":2954,"南投縣":222,"雲林縣":1220,"嘉義縣":1393,"屏東縣":1546,"台東縣":250,"花蓮縣":476,"澎湖縣":267,"基隆市":367,"新竹市":290,"嘉義市":381,"金門縣":null,"連江縣":null},{"年度":2000,"總計":null,"台灣地區":28055,"新北市":3618,"台北市":398,"桃園市":1596,"台中市":1940,"台南市":3255,"高雄市":2294,"宜蘭縣":727,"新竹縣":934,"苗栗縣":1072,"彰化縣":5258,"南投縣":334,"雲林縣":1165,"嘉義縣":1374,"屏東縣":1545,"台東縣":499,"花蓮縣":520,"澎湖縣":254,"基隆市":604,"新竹市":308,"嘉義市":360,"金門縣":null,"連江縣":null},{"年度":2001,"總計":null,"台灣地區":27261,"新北市":4919,"台北市":323,"桃園市":1201,"台中市":1273,"台南市":2445,"高雄市":2644,"宜蘭縣":558,"新竹縣":802,"苗栗縣":1003,"彰化縣":4577,"南投縣":349,"雲林縣":1978,"嘉義縣":1643,"屏東縣":1690,"台東縣":265,"花蓮縣":390,"澎湖縣":236,"基隆市":436,"新竹市":229,"嘉義市":300,"金門縣":null,"連江縣":null},{"年度":2002,"總計":null,"台灣地區":27500,"新北市":4308,"台北市":302,"桃園市":901,"台中市":1176,"台南市":4628,"高雄市":2396,"宜蘭縣":514,"新竹縣":760,"苗栗縣":1429,"彰化縣":4358,"南投縣":238,"雲林縣":1961,"嘉義縣":1242,"屏東縣":1555,"台東縣":206,"花蓮縣":341,"澎湖縣":143,"基隆市":201,"新竹市":475,"嘉義市":366,"金門縣":null,"連江縣":null},{"年度":2003,"總計":null,"台灣地區":24230,"新北市":2730,"台北市":372,"桃園市":993,"台中市":1056,"台南市":4045,"高雄市":2940,"宜蘭縣":575,"新竹縣":617,"苗栗縣":878,"彰化縣":362,"南投縣":697,"雲林縣":2411,"嘉義縣":2485,"屏東縣":1239,"台東縣":170,"花蓮縣":480,"澎湖縣":259,"基隆市":640,"新竹市":696,"嘉義市":585,"金門縣":null,"連江縣":null},{"年度":2004,"總計":null,"台灣地區":24602,"新北市":3332,"台北市":572,"桃園市":1127,"台中市":969,"台南市":4284,"高雄市":2982,"宜蘭縣":655,"新竹縣":744,"苗栗縣":1404,"彰化縣":871,"南投縣":652,"雲林縣":1726,"嘉義縣":1672,"屏東縣":1428,"台東縣":233,"花蓮縣":348,"澎湖縣":222,"基隆市":398,"新竹市":637,"嘉義市":346,"金門縣":null,"連江縣":null},{"年度":2005,"總計":null,"台灣地區":30444,"新北市":4404,"台北市":884,"桃園市":1760,"台中市":2011,"台南市":3467,"高雄市":4679,"宜蘭縣":633,"新竹縣":1079,"苗栗縣":851,"彰化縣":2252,"南投縣":502,"雲林縣":2102,"嘉義縣":1363,"屏東縣":1931,"台東縣":179,"花蓮縣":682,"澎湖縣":395,"基隆市":450,"新竹市":621,"嘉義市":199,"金門縣":null,"連江縣":null},{"年度":2006,"總計":null,"台灣地區":38004,"新北市":5793,"台北市":528,"桃園市":2176,"台中市":2992,"台南市":4189,"高雄市":6108,"宜蘭縣":870,"新竹縣":832,"苗栗縣":1373,"彰化縣":887,"南投縣":974,"雲林縣":2635,"嘉義縣":1344,"屏東縣":4048,"台東縣":539,"花蓮縣":761,"澎湖縣":478,"基隆市":601,"新竹市":606,"嘉義市":270,"金門縣":null,"連江縣":null},{"年度":2007,"總計":36004,"台灣地區":35573,"新北市":4760,"台北市":525,"桃園市":1784,"台中市":2187,"台南市":3535,"高雄市":5909,"宜蘭縣":678,"新竹縣":843,"苗栗縣":1360,"彰化縣":1089,"南投縣":864,"雲林縣":3274,"嘉義縣":1634,"屏東縣":2879,"台東縣":610,"花蓮縣":1081,"澎湖縣":342,"基隆市":529,"新竹市":893,"嘉義市":797,"金門縣":389,"連江縣":42},{"年度":2008,"總計":42804,"台灣地區":42197,"新北市":2820,"台北市":997,"桃園市":3076,"台中市":2484,"台南市":3699,"高雄市":5705,"宜蘭縣":1060,"新竹縣":1024,"苗栗縣":1208,"彰化縣":2894,"南投縣":1060,"雲林縣":2764,"嘉義縣":1916,"屏東縣":6924,"台東縣":1083,"花蓮縣":648,"澎湖縣":531,"基隆市":248,"新竹市":1050,"嘉義市":1006,"金門縣":587,"連江縣":20},{"年度":2009,"總計":44798,"台灣地區":44327,"新北市":2519,"台北市":1778,"桃園市":3851,"台中市":2630,"台南市":4365,"高雄市":7226,"宜蘭縣":1113,"新竹縣":1068,"苗栗縣":1642,"彰化縣":1561,"南投縣":2140,"雲林縣":3183,"嘉義縣":2051,"屏東縣":4403,"台東縣":1352,"花蓮縣":1033,"澎湖縣":722,"基隆市":283,"新竹市":554,"嘉義市":853,"金門縣":470,"連江縣":1},{"年度":2010,"總計":46834,"台灣地區":46355,"新北市":3743,"台北市":1542,"桃園市":4519,"台中市":3316,"台南市":3896,"高雄市":6268,"宜蘭縣":1355,"新竹縣":993,"苗栗縣":1265,"彰化縣":2583,"南投縣":1511,"雲林縣":2109,"嘉義縣":1912,"屏東縣":5346,"台東縣":1755,"花蓮縣":1362,"澎湖縣":597,"基隆市":213,"新竹市":1019,"嘉義市":1051,"金門縣":479,"連江縣":null},{"年度":2011,"總計":43118,"台灣地區":42570,"新北市":5815,"台北市":1520,"桃園市":3754,"台中市":2522,"台南市":3829,"高雄市":4363,"宜蘭縣":1249,"新竹縣":1052,"苗栗縣":1307,"彰化縣":1901,"南投縣":1207,"雲林縣":2131,"嘉義縣":2019,"屏東縣":4647,"台東縣":1155,"花蓮縣":1214,"澎湖縣":959,"基隆市":210,"新竹市":862,"嘉義市":854,"金門縣":529,"連江縣":19},{"年度":2012,"總計":36641,"台灣地區":36271,"新北市":4862,"台北市":2680,"桃園市":3658,"台中市":1751,"台南市":3554,"高雄市":4358,"宜蘭縣":1189,"新竹縣":1074,"苗栗縣":1240,"彰化縣":1925,"南投縣":782,"雲林縣":2075,"嘉義縣":2070,"屏東縣":2663,"台東縣":298,"花蓮縣":558,"澎湖縣":446,"基隆市":223,"新竹市":684,"嘉義市":181,"金門縣":370,"連江縣":null},{"年度":2013,"總計":33382,"台灣地區":32999,"新北市":4585,"台北市":1658,"桃園市":3662,"台中市":1231,"台南市":4714,"高雄市":3522,"宜蘭縣":1074,"新竹縣":1020,"苗栗縣":1156,"彰化縣":2001,"南投縣":582,"雲林縣":1742,"嘉義縣":1740,"屏東縣":1636,"台東縣":243,"花蓮縣":894,"澎湖縣":518,"基隆市":228,"新竹市":591,"嘉義市":202,"金門縣":367,"連江縣":16},{"年度":2014,"總計":34593,"台灣地區":34183,"新北市":5541,"台北市":2480,"桃園市":3847,"台中市":1850,"台南市":4203,"高雄市":3446,"宜蘭縣":751,"新竹縣":1501,"苗栗縣":719,"彰化縣":2514,"南投縣":375,"雲林縣":1513,"嘉義縣":1650,"屏東縣":1621,"台東縣":205,"花蓮縣":582,"澎湖縣":435,"基隆市":223,"新竹市":672,"嘉義市":55,"金門縣":391,"連江縣":19},{"年度":2015,"總計":35001,"台灣地區":34631,"新北市":5970,"台北市":1659,"桃園市":3714,"台中市":1951,"台南市":4381,"高雄市":3569,"宜蘭縣":1537,"新竹縣":1426,"苗栗縣":931,"彰化縣":2207,"南投縣":506,"雲林縣":1914,"嘉義縣":1656,"屏東縣":1205,"台東縣":236,"花蓮縣":448,"澎湖縣":389,"基隆市":225,"新竹市":478,"嘉義市":229,"金門縣":370,"連江縣":null},{"年度":2016,"總計":36261,"台灣地區":36046,"新北市":5921,"台北市":2659,"桃園市":4420,"台中市":2103,"台南市":4924,"高雄市":3680,"宜蘭縣":1019,"新竹縣":907,"苗栗縣":713,"彰化縣":2363,"南投縣":457,"雲林縣":1961,"嘉義縣":1788,"屏東縣":941,"台東縣":227,"花蓮縣":669,"澎湖縣":147,"基隆市":170,"新竹市":691,"嘉義市":286,"金門縣":215,"連江縣":null},{"年度":2017,"總計":41023,"台灣地區":40691,"新北市":7856,"台北市":2583,"桃園市":4392,"台中市":2071,"台南市":5209,"高雄市":2185,"宜蘭縣":795,"新竹縣":947,"苗栗縣":667,"彰化縣":3319,"南投縣":489,"雲林縣":3427,"嘉義縣":1487,"屏東縣":1919,"台東縣":335,"花蓮縣":1270,"澎湖縣":435,"基隆市":171,"新竹市":807,"嘉義市":327,"金門縣":323,"連江縣":9},{"年度":2018,"總計":41276,"台灣地區":41009,"新北市":7026,"台北市":2070,"桃園市":5530,"台中市":2241,"台南市":5029,"高雄市":2649,"宜蘭縣":793,"新竹縣":1182,"苗栗縣":863,"彰化縣":2357,"南投縣":627,"雲林縣":2475,"嘉義縣":1885,"屏東縣":2364,"台東縣":368,"花蓮縣":1910,"澎湖縣":394,"基隆市":183,"新竹市":773,"嘉義市":290,"金門縣":245,"連江縣":22}]