[{"年度":1998,"總計":10627,"台灣地區":10618,"新北市":1580,"台北市":1273,"桃園市":837,"台中市":957,"台南市":946,"高雄市":1370,"宜蘭縣":181,"新竹縣":247,"苗栗縣":252,"彰化縣":417,"南投縣":317,"雲林縣":216,"嘉義縣":158,"屏東縣":311,"台東縣":273,"花蓮縣":277,"澎湖縣":26,"基隆市":350,"新竹市":259,"嘉義市":277,"金門縣":9,"連江縣":null},{"年度":1999,"總計":9681,"台灣地區":9674,"新北市":1368,"台北市":1207,"桃園市":727,"台中市":875,"台南市":995,"高雄市":1355,"宜蘭縣":155,"新竹縣":222,"苗栗縣":203,"彰化縣":406,"南投縣":198,"雲林縣":181,"嘉義縣":197,"屏東縣":322,"台東縣":190,"花蓮縣":288,"澎湖縣":29,"基隆市":287,"新竹市":215,"嘉義市":162,"金門縣":7,"連江縣":null},{"年度":2000,"總計":8217,"台灣地區":8204,"新北市":1158,"台北市":832,"桃園市":551,"台中市":601,"台南市":716,"高雄市":1396,"宜蘭縣":223,"新竹縣":225,"苗栗縣":252,"彰化縣":405,"南投縣":155,"雲林縣":194,"嘉義縣":139,"屏東縣":286,"台東縣":188,"花蓮縣":207,"澎湖縣":21,"基隆市":252,"新竹市":189,"嘉義市":131,"金門縣":13,"連江縣":null},{"年度":2001,"總計":9595,"台灣地區":9585,"新北市":1383,"台北市":839,"桃園市":910,"台中市":789,"台南市":787,"高雄市":1317,"宜蘭縣":183,"新竹縣":157,"苗栗縣":289,"彰化縣":562,"南投縣":307,"雲林縣":224,"嘉義縣":187,"屏東縣":417,"台東縣":159,"花蓮縣":197,"澎湖縣":19,"基隆市":379,"新竹市":269,"嘉義市":158,"金門縣":10,"連江縣":null},{"年度":2002,"總計":9488,"台灣地區":9474,"新北市":1320,"台北市":846,"桃園市":987,"台中市":923,"台南市":743,"高雄市":1294,"宜蘭縣":202,"新竹縣":195,"苗栗縣":231,"彰化縣":442,"南投縣":258,"雲林縣":249,"嘉義縣":187,"屏東縣":412,"台東縣":160,"花蓮縣":211,"澎湖縣":35,"基隆市":274,"新竹市":308,"嘉義市":132,"金門縣":14,"連江縣":null},{"年度":2003,"總計":8580,"台灣地區":8567,"新北市":1120,"台北市":753,"桃園市":855,"台中市":815,"台南市":706,"高雄市":1187,"宜蘭縣":207,"新竹縣":171,"苗栗縣":194,"彰化縣":491,"南投縣":219,"雲林縣":272,"嘉義縣":188,"屏東縣":431,"台東縣":99,"花蓮縣":165,"澎湖縣":34,"基隆市":258,"新竹市":183,"嘉義市":183,"金門縣":12,"連江縣":1},{"年度":2004,"總計":7441,"台灣地區":7440,"新北市":1151,"台北市":728,"桃園市":601,"台中市":771,"台南市":504,"高雄市":1093,"宜蘭縣":166,"新竹縣":166,"苗栗縣":178,"彰化縣":353,"南投縣":214,"雲林縣":185,"嘉義縣":150,"屏東縣":372,"台東縣":109,"花蓮縣":133,"澎湖縣":33,"基隆市":214,"新竹市":172,"嘉義市":95,"金門縣":1,"連江縣":null},{"年度":2005,"總計":7508,"台灣地區":7502,"新北市":1116,"台北市":676,"桃園市":723,"台中市":799,"台南市":561,"高雄市":1134,"宜蘭縣":145,"新竹縣":136,"苗栗縣":235,"彰化縣":391,"南投縣":186,"雲林縣":166,"嘉義縣":124,"屏東縣":320,"台東縣":91,"花蓮縣":172,"澎湖縣":17,"基隆市":163,"新竹市":173,"嘉義市":135,"金門縣":6,"連江縣":null},{"年度":2006,"總計":7978,"台灣地區":7974,"新北市":1411,"台北市":720,"桃園市":841,"台中市":837,"台南市":478,"高雄市":1181,"宜蘭縣":157,"新竹縣":142,"苗栗縣":181,"彰化縣":365,"南投縣":187,"雲林縣":160,"嘉義縣":156,"屏東縣":380,"台東縣":95,"花蓮縣":171,"澎湖縣":15,"基隆市":153,"新竹市":198,"嘉義市":106,"金門縣":4,"連江縣":null},{"年度":2007,"總計":7529,"台灣地區":7522,"新北市":1513,"台北市":693,"桃園市":778,"台中市":840,"台南市":431,"高雄市":1104,"宜蘭縣":147,"新竹縣":165,"苗栗縣":131,"彰化縣":288,"南投縣":128,"雲林縣":216,"嘉義縣":93,"屏東縣":437,"台東縣":39,"花蓮縣":128,"澎湖縣":24,"基隆市":107,"新竹市":155,"嘉義市":89,"金門縣":7,"連江縣":null},{"年度":2008,"總計":6843,"台灣地區":6829,"新北市":1304,"台北市":707,"桃園市":693,"台中市":676,"台南市":477,"高雄市":1032,"宜蘭縣":104,"新竹縣":169,"苗栗縣":150,"彰化縣":236,"南投縣":147,"雲林縣":142,"嘉義縣":122,"屏東縣":306,"台東縣":56,"花蓮縣":118,"澎湖縣":19,"基隆市":107,"新竹市":160,"嘉義市":71,"金門縣":13,"連江縣":1},{"年度":2009,"總計":6139,"台灣地區":6124,"新北市":1234,"台北市":666,"桃園市":659,"台中市":507,"台南市":455,"高雄市":925,"宜蘭縣":112,"新竹縣":137,"苗栗縣":91,"彰化縣":221,"南投縣":128,"雲林縣":122,"嘉義縣":113,"屏東縣":295,"台東縣":39,"花蓮縣":98,"澎湖縣":17,"基隆市":90,"新竹市":109,"嘉義市":84,"金門縣":15,"連江縣":null},{"年度":2010,"總計":5365,"台灣地區":5358,"新北市":1110,"台北市":588,"桃園市":519,"台中市":381,"台南市":362,"高雄市":807,"宜蘭縣":85,"新竹縣":137,"苗栗縣":91,"彰化縣":221,"南投縣":87,"雲林縣":127,"嘉義縣":104,"屏東縣":322,"台東縣":50,"花蓮縣":99,"澎湖縣":8,"基隆市":98,"新竹市":98,"嘉義市":57,"金門縣":6,"連江縣":1},{"年度":2011,"總計":4929,"台灣地區":4892,"新北市":1078,"台北市":520,"桃園市":407,"台中市":356,"台南市":376,"高雄市":818,"宜蘭縣":56,"新竹縣":123,"苗栗縣":87,"彰化縣":119,"南投縣":90,"雲林縣":78,"嘉義縣":88,"屏東縣":248,"台東縣":54,"花蓮縣":109,"澎湖縣":10,"基隆市":109,"新竹市":96,"嘉義市":40,"金門縣":37,"連江縣":null},{"年度":2012,"總計":4527,"台灣地區":4509,"新北市":1300,"台北市":531,"桃園市":261,"台中市":368,"台南市":353,"高雄市":419,"宜蘭縣":87,"新竹縣":91,"苗栗縣":87,"彰化縣":150,"南投縣":137,"雲林縣":69,"嘉義縣":83,"屏東縣":170,"台東縣":21,"花蓮縣":69,"澎湖縣":21,"基隆市":117,"新竹市":125,"嘉義市":37,"金門縣":18,"連江縣":null},{"年度":2013,"總計":3052,"台灣地區":3037,"新北市":413,"台北市":503,"桃園市":220,"台中市":243,"台南市":267,"高雄市":337,"宜蘭縣":89,"新竹縣":53,"苗栗縣":83,"彰化縣":129,"南投縣":88,"雲林縣":50,"嘉義縣":66,"屏東縣":57,"台東縣":40,"花蓮縣":92,"澎湖縣":4,"基隆市":114,"新竹市":135,"嘉義市":31,"金門縣":9,"連江縣":6},{"年度":2014,"總計":2825,"台灣地區":2816,"新北市":329,"台北市":531,"桃園市":135,"台中市":217,"台南市":360,"高雄市":238,"宜蘭縣":106,"新竹縣":73,"苗栗縣":48,"彰化縣":143,"南投縣":90,"雲林縣":64,"嘉義縣":62,"屏東縣":38,"台東縣":9,"花蓮縣":101,"澎湖縣":3,"基隆市":109,"新竹市":112,"嘉義市":30,"金門縣":8,"連江縣":1},{"年度":2015,"總計":2522,"台灣地區":2504,"新北市":250,"台北市":382,"桃園市":193,"台中市":193,"台南市":302,"高雄市":213,"宜蘭縣":139,"新竹縣":74,"苗栗縣":36,"彰化縣":137,"南投縣":73,"雲林縣":48,"嘉義縣":127,"屏東縣":44,"台東縣":8,"花蓮縣":66,"澎湖縣":9,"基隆市":86,"新竹市":72,"嘉義市":40,"金門縣":18,"連江縣":null},{"年度":2016,"總計":2208,"台灣地區":2197,"新北市":270,"台北市":381,"桃園市":147,"台中市":209,"台南市":204,"高雄市":232,"宜蘭縣":52,"新竹縣":61,"苗栗縣":37,"彰化縣":115,"南投縣":64,"雲林縣":35,"嘉義縣":61,"屏東縣":47,"台東縣":10,"花蓮縣":83,"澎湖縣":5,"基隆市":79,"新竹市":54,"嘉義市":34,"金門縣":11,"連江縣":null},{"年度":2017,"總計":1910,"台灣地區":1890,"新北市":198,"台北市":254,"桃園市":155,"台中市":159,"台南市":123,"高雄市":248,"宜蘭縣":45,"新竹縣":43,"苗栗縣":46,"彰化縣":69,"南投縣":76,"雲林縣":53,"嘉義縣":66,"屏東縣":56,"台東縣":10,"花蓮縣":96,"澎湖縣":12,"基隆市":109,"新竹市":20,"嘉義市":30,"金門縣":20,"連江縣":null},{"年度":2018,"總計":1666,"台灣地區":1655,"新北市":178,"台北市":274,"桃園市":97,"台中市":124,"台南市":149,"高雄市":165,"宜蘭縣":55,"新竹縣":23,"苗栗縣":23,"彰化縣":77,"南投縣":101,"雲林縣":39,"嘉義縣":35,"屏東縣":101,"台東縣":1,"花蓮縣":58,"澎湖縣":4,"基隆市":102,"新竹市":8,"嘉義市":25,"金門縣":11,"連江縣":0}]