[{"年度":1998,"總計":null,"台灣地區":null,"新北市":null,"台北市":null,"桃園市":null,"台中市":null,"台南市":null,"高雄市":null,"宜蘭縣":null,"新竹縣":null,"苗栗縣":null,"彰化縣":null,"南投縣":null,"雲林縣":null,"嘉義縣":null,"屏東縣":null,"台東縣":null,"花蓮縣":null,"澎湖縣":null,"基隆市":null,"新竹市":null,"嘉義市":null,"金門縣":null,"連江縣":null},{"年度":1999,"總計":null,"台灣地區":null,"新北市":null,"台北市":null,"桃園市":null,"台中市":null,"台南市":null,"高雄市":null,"宜蘭縣":null,"新竹縣":null,"苗栗縣":null,"彰化縣":null,"南投縣":null,"雲林縣":null,"嘉義縣":null,"屏東縣":null,"台東縣":null,"花蓮縣":null,"澎湖縣":null,"基隆市":null,"新竹市":null,"嘉義市":null,"金門縣":null,"連江縣":null},{"年度":2000,"總計":null,"台灣地區":10862,"新北市":1651,"台北市":1949,"桃園市":557,"台中市":931,"台南市":674,"高雄市":1770,"宜蘭縣":227,"新竹縣":236,"苗栗縣":296,"彰化縣":442,"南投縣":228,"雲林縣":325,"嘉義縣":244,"屏東縣":423,"台東縣":201,"花蓮縣":226,"澎湖縣":90,"基隆市":155,"新竹市":163,"嘉義市":74,"金門縣":null,"連江縣":null},{"年度":2001,"總計":null,"台灣地區":11343,"新北市":1680,"台北市":2361,"桃園市":609,"台中市":985,"台南市":707,"高雄市":1716,"宜蘭縣":228,"新竹縣":221,"苗栗縣":298,"彰化縣":446,"南投縣":229,"雲林縣":304,"嘉義縣":223,"屏東縣":416,"台東縣":167,"花蓮縣":230,"澎湖縣":75,"基隆市":186,"新竹市":166,"嘉義市":96,"金門縣":null,"連江縣":null},{"年度":2002,"總計":null,"台灣地區":11979,"新北市":1812,"台北市":2349,"桃園市":690,"台中市":1050,"台南市":746,"高雄市":1782,"宜蘭縣":247,"新竹縣":223,"苗栗縣":325,"彰化縣":480,"南投縣":249,"雲林縣":341,"嘉義縣":271,"屏東縣":420,"台東縣":195,"花蓮縣":238,"澎湖縣":80,"基隆市":198,"新竹市":170,"嘉義市":113,"金門縣":null,"連江縣":null},{"年度":2003,"總計":null,"台灣地區":11524,"新北市":1777,"台北市":1726,"桃園市":722,"台中市":1092,"台南市":754,"高雄市":1772,"宜蘭縣":276,"新竹縣":223,"苗栗縣":350,"彰化縣":503,"南投縣":270,"雲林縣":341,"嘉義縣":305,"屏東縣":433,"台東縣":189,"花蓮縣":246,"澎湖縣":87,"基隆市":200,"新竹市":178,"嘉義市":80,"金門縣":null,"連江縣":null},{"年度":2004,"總計":12382,"台灣地區":12236,"新北市":1739,"台北市":2079,"桃園市":766,"台中市":1212,"台南市":816,"高雄市":1737,"宜蘭縣":299,"新竹縣":266,"苗栗縣":356,"彰化縣":518,"南投縣":290,"雲林縣":343,"嘉義縣":326,"屏東縣":441,"台東縣":203,"花蓮縣":263,"澎湖縣":90,"基隆市":173,"新竹市":192,"嘉義市":127,"金門縣":106,"連江縣":40},{"年度":2005,"總計":12638,"台灣地區":12456,"新北市":1815,"台北市":2157,"桃園市":830,"台中市":1223,"台南市":767,"高雄市":1698,"宜蘭縣":295,"新竹縣":289,"苗栗縣":371,"彰化縣":537,"南投縣":290,"雲林縣":363,"嘉義縣":335,"屏東縣":449,"台東縣":230,"花蓮縣":272,"澎湖縣":81,"基隆市":198,"新竹市":124,"嘉義市":132,"金門縣":124,"連江縣":58},{"年度":2006,"總計":12952,"台灣地區":12765,"新北市":1908,"台北市":2136,"桃園市":823,"台中市":1220,"台南市":836,"高雄市":1739,"宜蘭縣":291,"新竹縣":269,"苗栗縣":372,"彰化縣":557,"南投縣":291,"雲林縣":363,"嘉義縣":348,"屏東縣":468,"台東縣":243,"花蓮縣":279,"澎湖縣":97,"基隆市":210,"新竹市":183,"嘉義市":132,"金門縣":119,"連江縣":68},{"年度":2007,"總計":14233,"台灣地區":14032,"新北市":2005,"台北市":3014,"桃園市":845,"台中市":1267,"台南市":864,"高雄市":1841,"宜蘭縣":309,"新竹縣":266,"苗栗縣":374,"彰化縣":563,"南投縣":292,"雲林縣":374,"嘉義縣":362,"屏東縣":464,"台東縣":242,"花蓮縣":276,"澎湖縣":108,"基隆市":220,"新竹市":204,"嘉義市":142,"金門縣":133,"連江縣":68},{"年度":2008,"總計":14794,"台灣地區":14585,"新北市":2052,"台北市":2986,"桃園市":939,"台中市":1290,"台南市":930,"高雄市":1921,"宜蘭縣":326,"新竹縣":300,"苗栗縣":395,"彰化縣":585,"南投縣":318,"雲林縣":412,"嘉義縣":411,"屏東縣":527,"台東縣":227,"花蓮縣":284,"澎湖縣":109,"基隆市":225,"新竹市":205,"嘉義市":143,"金門縣":141,"連江縣":68},{"年度":2009,"總計":14666,"台灣地區":14441,"新北市":2183,"台北市":2270,"桃園市":1013,"台中市":1331,"台南市":1059,"高雄市":1816,"宜蘭縣":367,"新竹縣":331,"苗栗縣":416,"彰化縣":634,"南投縣":352,"雲林縣":446,"嘉義縣":418,"屏東縣":544,"台東縣":225,"花蓮縣":302,"澎湖縣":116,"基隆市":275,"新竹市":200,"嘉義市":143,"金門縣":156,"連江縣":69},{"年度":2010,"總計":14937,"台灣地區":14708,"新北市":2318,"台北市":2286,"桃園市":1002,"台中市":1375,"台南市":1040,"高雄市":1837,"宜蘭縣":375,"新竹縣":327,"苗栗縣":423,"彰化縣":639,"南投縣":339,"雲林縣":468,"嘉義縣":433,"屏東縣":551,"台東縣":235,"花蓮縣":279,"澎湖縣":121,"基隆市":320,"新竹市":201,"嘉義市":139,"金門縣":159,"連江縣":70},{"年度":2011,"總計":15673,"台灣地區":15443,"新北市":2439,"台北市":2584,"桃園市":1116,"台中市":1416,"台南市":1125,"高雄市":1821,"宜蘭縣":398,"新竹縣":331,"苗栗縣":430,"彰化縣":668,"南投縣":353,"雲林縣":467,"嘉義縣":425,"屏東縣":544,"台東縣":237,"花蓮縣":292,"澎湖縣":127,"基隆市":314,"新竹市":211,"嘉義市":145,"金門縣":160,"連江縣":70},{"年度":2012,"總計":16026,"台灣地區":15759,"新北市":2463,"台北市":2711,"桃園市":1072,"台中市":1471,"台南市":1170,"高雄市":1844,"宜蘭縣":396,"新竹縣":332,"苗栗縣":427,"彰化縣":687,"南投縣":355,"雲林縣":509,"嘉義縣":421,"屏東縣":557,"台東縣":222,"花蓮縣":317,"澎湖縣":125,"基隆市":318,"新竹市":206,"嘉義市":156,"金門縣":182,"連江縣":85},{"年度":2013,"總計":15914,"台灣地區":15647,"新北市":2451,"台北市":2815,"桃園市":1065,"台中市":1398,"台南市":1132,"高雄市":1837,"宜蘭縣":397,"新竹縣":335,"苗栗縣":412,"彰化縣":684,"南投縣":345,"雲林縣":476,"嘉義縣":418,"屏東縣":554,"台東縣":235,"花蓮縣":316,"澎湖縣":125,"基隆市":305,"新竹市":193,"嘉義市":154,"金門縣":197,"連江縣":70},{"年度":2014,"總計":15873,"台灣地區":15589,"新北市":2440,"台北市":2685,"桃園市":1119,"台中市":1458,"台南市":1133,"高雄市":1801,"宜蘭縣":396,"新竹縣":328,"苗栗縣":444,"彰化縣":724,"南投縣":347,"雲林縣":491,"嘉義縣":399,"屏東縣":555,"台東縣":233,"花蓮縣":304,"澎湖縣":125,"基隆市":255,"新竹市":206,"嘉義市":146,"金門縣":215,"連江縣":69},{"年度":2015,"總計":10522,"台灣地區":10359,"新北市":2149,"台北市":846,"桃園市":799,"台中市":1208,"台南市":871,"高雄市":1034,"宜蘭縣":311,"新竹縣":298,"苗栗縣":165,"彰化縣":577,"南投縣":284,"雲林縣":274,"嘉義縣":220,"屏東縣":413,"台東縣":113,"花蓮縣":238,"澎湖縣":68,"基隆市":206,"新竹市":161,"嘉義市":124,"金門縣":140,"連江縣":23},{"年度":2016,"總計":11050,"台灣地區":10878,"新北市":2121,"台北市":851,"桃園市":813,"台中市":1326,"台南市":878,"高雄市":1080,"宜蘭縣":319,"新竹縣":332,"苗栗縣":215,"彰化縣":592,"南投縣":281,"雲林縣":408,"嘉義縣":264,"屏東縣":449,"台東縣":118,"花蓮縣":235,"澎湖縣":86,"基隆市":209,"新竹市":172,"嘉義市":129,"金門縣":147,"連江縣":25},{"年度":2017,"總計":11171,"台灣地區":10968,"新北市":2078,"台北市":880,"桃園市":873,"台中市":1277,"台南市":891,"高雄市":1063,"宜蘭縣":324,"新竹縣":339,"苗栗縣":245,"彰化縣":603,"南投縣":290,"雲林縣":415,"嘉義縣":260,"屏東縣":452,"台東縣":140,"花蓮縣":233,"澎湖縣":93,"基隆市":212,"新竹市":175,"嘉義市":125,"金門縣":155,"連江縣":48},{"年度":2018,"總計":11362,"台灣地區":11160,"新北市":2118,"台北市":903,"桃園市":896,"台中市":1290,"台南市":907,"高雄市":1074,"宜蘭縣":319,"新竹縣":345,"苗栗縣":264,"彰化縣":603,"南投縣":294,"雲林縣":428,"嘉義縣":258,"屏東縣":461,"台東縣":154,"花蓮縣":234,"澎湖縣":100,"基隆市":207,"新竹市":175,"嘉義市":130,"金門縣":155,"連江縣":47}]