[{"年度":1998,"總計":306,"台灣地區":305,"新北市":42,"台北市":34,"桃園市":36,"台中市":52,"台南市":21,"高雄市":26,"宜蘭縣":7,"新竹縣":2,"苗栗縣":8,"彰化縣":6,"南投縣":9,"雲林縣":6,"嘉義縣":6,"屏東縣":9,"台東縣":1,"花蓮縣":6,"澎湖縣":4,"基隆市":13,"新竹市":10,"嘉義市":7,"金門縣":1,"連江縣":null},{"年度":1999,"總計":230,"台灣地區":229,"新北市":52,"台北市":20,"桃園市":15,"台中市":15,"台南市":8,"高雄市":22,"宜蘭縣":11,"新竹縣":12,"苗栗縣":15,"彰化縣":7,"南投縣":9,"雲林縣":8,"嘉義縣":3,"屏東縣":6,"台東縣":5,"花蓮縣":2,"澎湖縣":null,"基隆市":14,"新竹市":1,"嘉義市":4,"金門縣":1,"連江縣":null},{"年度":2000,"總計":262,"台灣地區":261,"新北市":45,"台北市":18,"桃園市":30,"台中市":33,"台南市":16,"高雄市":21,"宜蘭縣":13,"新竹縣":8,"苗栗縣":6,"彰化縣":18,"南投縣":13,"雲林縣":4,"嘉義縣":13,"屏東縣":4,"台東縣":1,"花蓮縣":6,"澎湖縣":null,"基隆市":6,"新竹市":4,"嘉義市":2,"金門縣":null,"連江縣":1},{"年度":2001,"總計":234,"台灣地區":234,"新北市":27,"台北市":16,"桃園市":25,"台中市":34,"台南市":22,"高雄市":19,"宜蘭縣":5,"新竹縣":13,"苗栗縣":7,"彰化縣":17,"南投縣":6,"雲林縣":8,"嘉義縣":4,"屏東縣":7,"台東縣":1,"花蓮縣":7,"澎湖縣":null,"基隆市":7,"新竹市":8,"嘉義市":1,"金門縣":null,"連江縣":null},{"年度":2002,"總計":193,"台灣地區":191,"新北市":27,"台北市":13,"桃園市":22,"台中市":21,"台南市":23,"高雄市":8,"宜蘭縣":2,"新竹縣":6,"苗栗縣":5,"彰化縣":19,"南投縣":8,"雲林縣":6,"嘉義縣":13,"屏東縣":5,"台東縣":2,"花蓮縣":4,"澎湖縣":1,"基隆市":4,"新竹市":2,"嘉義市":null,"金門縣":2,"連江縣":null},{"年度":2003,"總計":228,"台灣地區":223,"新北市":43,"台北市":16,"桃園市":14,"台中市":46,"台南市":15,"高雄市":18,"宜蘭縣":10,"新竹縣":3,"苗栗縣":9,"彰化縣":11,"南投縣":3,"雲林縣":6,"嘉義縣":9,"屏東縣":6,"台東縣":3,"花蓮縣":6,"澎湖縣":null,"基隆市":null,"新竹市":2,"嘉義市":3,"金門縣":1,"連江縣":4},{"年度":2004,"總計":160,"台灣地區":160,"新北市":33,"台北市":10,"桃園市":11,"台中市":18,"台南市":13,"高雄市":7,"宜蘭縣":6,"新竹縣":6,"苗栗縣":5,"彰化縣":7,"南投縣":6,"雲林縣":8,"嘉義縣":9,"屏東縣":4,"台東縣":2,"花蓮縣":3,"澎湖縣":1,"基隆市":10,"新竹市":1,"嘉義市":null,"金門縣":null,"連江縣":null},{"年度":2005,"總計":139,"台灣地區":139,"新北市":24,"台北市":5,"桃園市":11,"台中市":32,"台南市":8,"高雄市":8,"宜蘭縣":1,"新竹縣":8,"苗栗縣":6,"彰化縣":4,"南投縣":2,"雲林縣":4,"嘉義縣":1,"屏東縣":3,"台東縣":2,"花蓮縣":8,"澎湖縣":null,"基隆市":7,"新竹市":1,"嘉義市":4,"金門縣":null,"連江縣":null},{"年度":2006,"總計":125,"台灣地區":125,"新北市":17,"台北市":2,"桃園市":22,"台中市":21,"台南市":5,"高雄市":11,"宜蘭縣":3,"新竹縣":2,"苗栗縣":2,"彰化縣":7,"南投縣":5,"雲林縣":3,"嘉義縣":2,"屏東縣":2,"台東縣":4,"花蓮縣":5,"澎湖縣":1,"基隆市":4,"新竹市":4,"嘉義市":3,"金門縣":null,"連江縣":null},{"年度":2007,"總計":120,"台灣地區":119,"新北市":15,"台北市":4,"桃園市":12,"台中市":22,"台南市":5,"高雄市":14,"宜蘭縣":3,"新竹縣":null,"苗栗縣":7,"彰化縣":10,"南投縣":4,"雲林縣":2,"嘉義縣":5,"屏東縣":8,"台東縣":1,"花蓮縣":3,"澎湖縣":1,"基隆市":3,"新竹市":null,"嘉義市":null,"金門縣":1,"連江縣":null},{"年度":2008,"總計":101,"台灣地區":101,"新北市":9,"台北市":3,"桃園市":12,"台中市":18,"台南市":5,"高雄市":14,"宜蘭縣":2,"新竹縣":2,"苗栗縣":1,"彰化縣":7,"南投縣":7,"雲林縣":8,"嘉義縣":2,"屏東縣":4,"台東縣":1,"花蓮縣":2,"澎湖縣":null,"基隆市":1,"新竹市":null,"嘉義市":2,"金門縣":null,"連江縣":null},{"年度":2009,"總計":117,"台灣地區":115,"新北市":17,"台北市":18,"桃園市":7,"台中市":9,"台南市":6,"高雄市":11,"宜蘭縣":4,"新竹縣":2,"苗栗縣":7,"彰化縣":6,"南投縣":3,"雲林縣":5,"嘉義縣":4,"屏東縣":2,"台東縣":2,"花蓮縣":5,"澎湖縣":null,"基隆市":4,"新竹市":null,"嘉義市":null,"金門縣":2,"連江縣":null},{"年度":2010,"總計":83,"台灣地區":83,"新北市":14,"台北市":4,"桃園市":12,"台中市":14,"台南市":4,"高雄市":3,"宜蘭縣":null,"新竹縣":1,"苗栗縣":1,"彰化縣":7,"南投縣":2,"雲林縣":5,"嘉義縣":5,"屏東縣":4,"台東縣":2,"花蓮縣":null,"澎湖縣":null,"基隆市":1,"新竹市":4,"嘉義市":null,"金門縣":null,"連江縣":null},{"年度":2011,"總計":97,"台灣地區":97,"新北市":17,"台北市":1,"桃園市":11,"台中市":28,"台南市":7,"高雄市":1,"宜蘭縣":4,"新竹縣":4,"苗栗縣":3,"彰化縣":3,"南投縣":3,"雲林縣":1,"嘉義縣":4,"屏東縣":1,"台東縣":null,"花蓮縣":2,"澎湖縣":1,"基隆市":3,"新竹市":null,"嘉義市":null,"金門縣":null,"連江縣":null},{"年度":2012,"總計":142,"台灣地區":142,"新北市":15,"台北市":14,"桃園市":15,"台中市":21,"台南市":23,"高雄市":4,"宜蘭縣":1,"新竹縣":null,"苗栗縣":2,"彰化縣":8,"南投縣":7,"雲林縣":5,"嘉義縣":6,"屏東縣":4,"台東縣":2,"花蓮縣":1,"澎湖縣":null,"基隆市":5,"新竹市":6,"嘉義市":1,"金門縣":null,"連江縣":null},{"年度":2013,"總計":92,"台灣地區":92,"新北市":8,"台北市":10,"桃園市":7,"台中市":10,"台南市":11,"高雄市":11,"宜蘭縣":5,"新竹縣":2,"苗栗縣":null,"彰化縣":5,"南投縣":4,"雲林縣":3,"嘉義縣":3,"屏東縣":1,"台東縣":3,"花蓮縣":1,"澎湖縣":null,"基隆市":4,"新竹市":null,"嘉義市":2,"金門縣":null,"連江縣":null},{"年度":2014,"總計":124,"台灣地區":124,"新北市":16,"台北市":10,"桃園市":5,"台中市":14,"台南市":11,"高雄市":4,"宜蘭縣":4,"新竹縣":1,"苗栗縣":8,"彰化縣":11,"南投縣":7,"雲林縣":3,"嘉義縣":9,"屏東縣":6,"台東縣":1,"花蓮縣":5,"澎湖縣":1,"基隆市":1,"新竹市":4,"嘉義市":3,"金門縣":null,"連江縣":null},{"年度":2015,"總計":117,"台灣地區":116,"新北市":17,"台北市":5,"桃園市":24,"台中市":6,"台南市":13,"高雄市":3,"宜蘭縣":null,"新竹縣":1,"苗栗縣":14,"彰化縣":6,"南投縣":4,"雲林縣":3,"嘉義縣":7,"屏東縣":3,"台東縣":1,"花蓮縣":6,"澎湖縣":1,"基隆市":2,"新竹市":null,"嘉義市":null,"金門縣":1,"連江縣":null},{"年度":2016,"總計":169,"台灣地區":169,"新北市":27,"台北市":17,"桃園市":22,"台中市":23,"台南市":16,"高雄市":13,"宜蘭縣":6,"新竹縣":5,"苗栗縣":6,"彰化縣":8,"南投縣":3,"雲林縣":4,"嘉義縣":2,"屏東縣":6,"台東縣":6,"花蓮縣":4,"澎湖縣":null,"基隆市":null,"新竹市":null,"嘉義市":1,"金門縣":null,"連江縣":null},{"年度":2017,"總計":178,"台灣地區":178,"新北市":34,"台北市":22,"桃園市":21,"台中市":22,"台南市":8,"高雄市":18,"宜蘭縣":4,"新竹縣":3,"苗栗縣":6,"彰化縣":10,"南投縣":2,"雲林縣":5,"嘉義縣":3,"屏東縣":7,"台東縣":2,"花蓮縣":3,"澎湖縣":null,"基隆市":6,"新竹市":null,"嘉義市":2,"金門縣":null,"連江縣":null},{"年度":2018,"總計":173,"台灣地區":173,"新北市":41,"台北市":16,"桃園市":21,"台中市":23,"台南市":9,"高雄市":13,"宜蘭縣":5,"新竹縣":1,"苗栗縣":2,"彰化縣":12,"南投縣":4,"雲林縣":6,"嘉義縣":2,"屏東縣":8,"台東縣":2,"花蓮縣":1,"澎湖縣":0,"基隆市":5,"新竹市":1,"嘉義市":1,"金門縣":0,"連江縣":0}]